lynxx/__init__.py
lynxx/align.py
lynxx/animations.py
lynxx/ansi.py
lynxx/colors.py
lynxx/display.py
lynxx/pattern.py
lynxx/py.typed
lynxx/system.py
lynxx/typess.py
lynxx-1.2.dist-info/METADATA
lynxx-1.2.dist-info/WHEEL
lynxx-1.2.dist-info/RECORD
