Metadata-Version: 2.1
Name: Lynxx
Version: 1.2
Summary: A Python package to make your programs easy to use and nice to look at
License: GNU GPL V3
Keywords: tui,python,style,colors,pystyle
Author: BlueRed
Author-email: izak57k@gmail.com
Requires-Python: >=3.10,<4.0
Classifier: Environment :: Console
Classifier: Intended Audience :: Developers
Classifier: License :: OSI Approved :: GNU Affero General Public License v3
Classifier: License :: Other/Proprietary License
Classifier: Operating System :: OS Independent
Classifier: Programming Language :: Python :: 3
Classifier: Programming Language :: Python :: 3.10
Classifier: Programming Language :: Python :: 3.11
Classifier: Programming Language :: Python :: 3.12
Classifier: Topic :: Desktop Environment
Classifier: Topic :: Software Development
Classifier: Topic :: Software Development :: User Interfaces
Classifier: Topic :: Terminals
Classifier: Topic :: Utilities
Classifier: Typing :: Typed
Requires-Dist: keyboard (>=0.13.5,<0.14.0)
